<?xml version="1.0" encoding="UTF-8"?>
<!--
To change this template, choose Tools | Templates
and open the template in the editor.
-->
<Panel id="startingPanel" xmlns:a="urn:import:org.asi.ui.extfilteringtable" xmlns:b="urn:import:org.asi.ui.customtextfield" >
    <VerticalLayout id="mainLayout" margin="false"
                    spacing="false"  >
        <Panel  styleName="adjustCaption" caption="Selection Criteria" >
            <HorizontalLayout margin="true"
                              spacing="true" >
                <Label Value="Item No: " contentMode="HTML" />
                <TextField id="itemNo" inputPrompt="" />

                <Label Value="Item Name: " contentMode="HTML"  />
                <TextField id="itemName" inputPrompt="" />

                <Label Value="Item Desc: " contentMode="HTML" />
                <TextField id="itemDesc" inputPrompt="" />

                <Label Value="Therapeutic Class: " contentMode="HTML" />
                <TextField id="therapeuticClass" inputPrompt="" />

                <Label Value="Brand: " contentMode="HTML" />
                <TextField id="brand" inputPrompt="" />

            </HorizontalLayout>
        </Panel>
        
        <Panel  caption="Item Search" width="100%" styleName="adjustCaption" >
            <HorizontalLayout>      
                <VerticalLayout  id="searchCri" margin="false"
                                 spacing="false" styleName = "width-auto" >
                    <HorizontalLayout margin="true"
                                      spacing="true">
                     
                        <GridLayout columns="2"
                                    rows="1" spacing="true" styleName = "forecast-tab">
                            <GridLayout margin="true" spacing="true" columns="8"
                                        rows="4" styleName = "forecast-tab">

                                <Label caption="Contract Holder:" contentMode="HTML" />
                                <b:CustomTextField id="contractHolder" inputPrompt="" immediate="true"
                                                   styleName="searchicon" />
                     
                                <Label caption="Market Type:" contentMode="HTML" />
                                <ComboBox id="marketType"  nullSelectionAllowed="true" inputPrompt="-Select One-"
                                          immediate="true" styleName="comboxsize"/>
                    
                                <Label caption="Company Family Plan:" contentMode="HTML" />
                                <b:CustomTextField id="cfp" inputPrompt="" immediate="true"
                                                   styleName="searchicon" />
                                
                                <Button id="allItemsBtn" caption="All Items"  styleName="link"/>
                                   <ComboBox id="allItemsCombo" />
                                
                                
                                <Label caption="Contract No:" contentMode="HTML" />
                                <b:CustomTextField id="contractNo" inputPrompt="" immediate="true"
                                                   styleName="searchicon" />
                    
                                <Label caption="Start Date: " contentMode="HTML" />
                                <PopupDateField id="startDate" dateFormat="MM/dd/yyyy" styleName="align-center"/>
                    
                                <Label caption="Item Family Plan:" contentMode="HTML" />
                                <b:CustomTextField id="ifp" inputPrompt="" immediate="true"
                                                   styleName="searchicon" />
                                <Label caption="" contentMode="HTML" />
                                <Label caption="" contentMode="HTML" />
                    
                                <Label caption="Contract Name:" contentMode="HTML" />
                                <b:CustomTextField id="contractName" inputPrompt="" immediate="true"
                                                   styleName="searchicon" />
                                <Label caption="End Date: " contentMode="HTML" />
                                <PopupDateField id="endDate" dateFormat="MM/dd/yyyy" styleName="align-center"/>
                    
                                <Label caption="Price Schedule:" contentMode="HTML" />
                                <b:CustomTextField id="priceSchedule" inputPrompt="" immediate="true"
                                                   styleName="searchicon" />
                                
                                <Label caption="" contentMode="HTML" />
                                <Label caption="" contentMode="HTML" />
                                
                                <Label caption="Customer No:" contentMode="HTML" />
                                <b:CustomTextField id="customerNo" inputPrompt="" immediate="true"
                                                   styleName="searchicon" />
                                <Label caption="Customer Name:" contentMode="HTML" />
                                <b:CustomTextField id="customerName" inputPrompt="" immediate="true"
                                                   styleName="searchicon" />
                                <Label caption="Rebate Schedule:" contentMode="HTML" />
                                <b:CustomTextField id="rebateSchedule" inputPrompt="" immediate="true"
                                                   styleName="searchicon" />
                                
                                <Label caption="" contentMode="HTML" />
                                <Label caption="" contentMode="HTML" />
                            </GridLayout>
<!--                            <GridLayout columns="3"
                                    rows="1" spacing="true" styleName = "forecast-tab">
                                  <Button id="allItemsBtn" caption="All Items"  styleName="link"/>
                                   <ComboBox id="allItemsCombo" />
                            </GridLayout>-->
                            <Panel  styleName="adjustCaption" id="aliasDetails" caption="Alias Details">
                                <GridLayout id="gridLayout" spacing="true" margin="true"
                                            immediate="true" columns="4" rows="2">
                                    <Label caption="Type: " contentMode="HTML" />
                                    <ComboBox id="typeDdlb" nullSelectionAllowed="false" 
                                              immediate="true" styleName="comboxsize" />
                                    <Label caption="From: " contentMode="HTML" />
                                    <PopupDateField id="fromDate" dateFormat="MM/dd/yyyy" styleName="align-center"/>
                        
                                    <Label caption="Number:" contentMode="HTML" />
                                    <TextField id="number" inputPrompt="" /> 
                    
                                    <Label caption="To: " contentMode="HTML" />
                                    <PopupDateField id="toDate" dateFormat="MM/dd/yyyy" styleName="align-center"/>
                                </GridLayout>
                            </Panel>
                        </GridLayout>
                    </HorizontalLayout>
                    <HorizontalLayout>
                        <Button caption="RESET" id="resetBtn" />
                        <Button caption="SEARCH" id="searchBtn" />
                    </HorizontalLayout>
                </VerticalLayout>
            </HorizontalLayout>
        </Panel>
       
        <Panel  styleName="adjustCaption" id="MassUpdatePanel1" caption="Mass Update">
            <HorizontalLayout id="horizontalLayout3" spacing="true" margin="true" immediate="true">
                <GridLayout spacing="true"  id="MassUpdateLayout" immediate="true" columns="13" rows="1">
                    <OptionGroup multiSelect="false" id="massUpdateRadio" immediate="true" enable="true" styleName = "horizontal"/>
                    <Label Value="Field:" contentMode="HTML" />
                    <ComboBox id="field" immediate="true" width="199px" />
                    <Label Value="Value:" id="valuelabel" contentMode="HTML" />
                    <ComboBox id="massUpdateValue" immediate="true" />
                    <b:CustomTextField id="massUpdateText"/>
                    <Label  id="startdatelabel" contentMode="HTML"/>
                    <PopupDateField id="massStartDate" dateFormat="MM/dd/yyyy"  styleName="align-center"/>
                    <Label  id="enddatelabel" contentMode="HTML" />
                    <PopupDateField id="massEndDate" dateFormat="MM/dd/yyyy" styleName="align-center"/>
                    <TextField id="baseWacManual" />
                    <PopupDateField id="baseWacDate" dateFormat="MM/dd/yyyy" styleName="align-center"/>
                    <ComboBox id="baseWacPriceType" styleName="comboxsize" enable="true" nullSelectionAllowed="true" immediate="true" />
                    <Button id="populateBtn" caption="POPULATE" />
                </GridLayout>
                
            </HorizontalLayout>
        </Panel>
        <HorizontalLayout>  
            
            <Panel  styleName="adjustCaption" id="AddItemDetails" caption="Add Item Details">
                <VerticalLayout styleName = "width-auto">    
                       
                    <VerticalLayout styleName = "width-auto" id="contractVertical" margin="false"
                                    spacing="true" >
                    </VerticalLayout>  
                    <!--<Table id="currentContractTable" width="1100px" immediate="true" height="200px"/>-->
                    <!--                      <a:ExtFilterTable  styleName="table-header-normal"
                                id="currentContractTable" width="1100px" immediate="true" height="200px" />
                    -->                
                    <HorizontalLayout margin="true" spacing="false">
                        <Button caption="RESET" id="resetBtncur" />
                      
                        <Button caption="SUBMIT" id="submitBtncur" />
                    </HorizontalLayout>
                </VerticalLayout>
            </Panel>
       
        </HorizontalLayout>
         
        <!--<Panel  styleName="adjustCaption" id="componentInformation" caption="Component Information">-->
            <HorizontalLayout>      
                <VerticalLayout styleName = "width-auto">     
                <VerticalLayout styleName = "width-auto" id="componentInfoLayout"></VerticalLayout>
<!--                <GridLayout  spacing="true" columns="10"
                            rows="2">
                    <Label Value="Component Selection:" contentMode="HTML" />
                    <ComboBox id="componentSelection" immediate="true" width="199px" />
                    <Label Value="RS Number:" contentMode="HTML"  />
                    <TextField id="rsNumber" inputPrompt="" /> 

                    <Label Value="Status :" contentMode="HTML"  />
                    <TextField id="status" inputPrompt="" />                                   
                
                        <Label Value="Rebate Frequency:" contentMode="HTML"  />
                        <TextField id="rebateFrequency" inputPrompt="" />
                        <Label Value="Start Date: " contentMode="HTML"  />
                        <PopupDateField id="startDatecomponent" dateFormat="dd/M/yyyy" />
                        <Label Value="RS ID:" contentMode="HTML"  />
                        <TextField id="rsId" inputPrompt="" />                                   
                        <Label Value="RS Name:" contentMode="HTML"  />
                        <TextField id="rsName" inputPrompt="" />                                   
                        <Label Value="RAR Type" contentMode="HTML"  />
                        <TextField id="rarType" inputPrompt="" />                                   
                        <Label Value="Basis :" contentMode="HTML" />
                        <TextField id="basis" inputPrompt="" />                                   
                        <Label Value="End Date: " contentMode="HTML"  />
                        <PopupDateField id="endDatecomp" dateFormat="dd/M/yyyy" />
                    </GridLayout>-->
                    <!--<Table id="componentInformationTable" width="1100px" immediate="true" height="200px"/>-->
                    <!--       <a:ExtFilterTable  styleName="table-header-normal"
                    id="componentInforamtionTable" width="1100px" immediate="true" height="200px" />              -->
<!--                    <Button caption="" id="exportBtn" />-->

                </VerticalLayout>
            </HorizontalLayout>   
        <!--</Panel>-->
    </VerticalLayout>
</Panel>

